starccato_jax/__init__.py
starccato_jax/_version.py
starccato_jax/credible_intervals.py
starccato_jax/logging.py
starccato_jax/starccato_model.py
starccato_jax/waveforms.py
starccato_jax/data/__init__.py
starccato_jax/data/default_weights.py
starccato_jax/data/downloader.py
starccato_jax/data/training_data.py
starccato_jax/data/urls.py
starccato_jax/data/datasets/__init__.py
starccato_jax/data/datasets/blip_glitches.py
starccato_jax/data/datasets/richers_ccsne.py
starccato_jax/pca/__init__.py
starccato_jax/pca/pca.py
starccato_jax/pca/starccato_pca.py
starccato_jax/plotting/__init__.py
starccato_jax/plotting/gif_generator.py
starccato_jax/plotting/plot_distributions.py
starccato_jax/plotting/plot_gradients.py
starccato_jax/plotting/plot_latent_kl.py
starccato_jax/plotting/plot_reconstructions.py
starccato_jax/plotting/plot_training_metrics.py
starccato_jax/plotting/utils.py
starccato_jax/vae/__init__.py
starccato_jax/vae/cli.py
starccato_jax/vae/config.py
starccato_jax/vae/starccato_vae.py
starccato_jax/vae/core/__init__.py
starccato_jax/vae/core/data_containers.py
starccato_jax/vae/core/io.py
starccato_jax/vae/core/loss.py
starccato_jax/vae/core/model.py
starccato_jax/vae/core/trainer/__init__.py
starccato_jax/vae/core/trainer/plot_utils.py
starccato_jax/vae/core/trainer/trainer.py
starccato_jax-0.2.0.dist-info/METADATA
starccato_jax-0.2.0.dist-info/WHEEL
starccato_jax-0.2.0.dist-info/entry_points.txt
starccato_jax-0.2.0.dist-info/top_level.txt
starccato_jax-0.2.0.dist-info/RECORD
